signifikante/__init__.py
signifikante/algo.py
signifikante/core.py
signifikante/fdr.py
signifikante/fdr_utils.py
signifikante/utils.py
signifikante-0.1.1.dist-info/METADATA
signifikante-0.1.1.dist-info/WHEEL
signifikante-0.1.1.dist-info/licenses/LICENSE
signifikante-0.1.1.dist-info/RECORD
