Metadata-Version: 2.4
Name: signifikante
Version: 0.1.1
Summary: Scalable gene regulatory network inference using tree-based ensemble regressors with p-values
Project-URL: Homepage, https://github.com/bionetslab/SignifiKANTE
Author-email: Anne Hartebrodt <anne.hartebrodt@fau.de>, Fabian Woller <fabian.woller@fau.de>, Paul Martini <paul.martini@fau.de>, Thomas Moerman <thomas.moerman@gmail.com>
License: GNU General Public License v3 (GPLv3)
License-File: LICENSE
Classifier: License :: OSI Approved :: GNU General Public License v3 (GPLv3)
Classifier: Operating System :: OS Independent
Classifier: Programming Language :: Python :: 3
Requires-Python: <3.14,>=3.10
Requires-Dist: dask
Requires-Dist: distributed
Requires-Dist: numba
Requires-Dist: numpy<2.0
Requires-Dist: pandas
Requires-Dist: pyarrow
Requires-Dist: pytest
Requires-Dist: scikit-learn
Requires-Dist: scikit-learn-extra
Requires-Dist: scipy
Requires-Dist: setuptools
Requires-Dist: sparse
Requires-Dist: statsmodels
Requires-Dist: xgboost
